[
	{
		"id": 0,
		"label": "G",
		"theme": "lobby",
		"ambient_color": [
			0.42,
			0.44,
			0.4
		],
		"zones": [
			{
				"type": "ZONE_LOBBY",
				"x": 0,
				"y": 8,
				"w": 320,
				"h": 52
			},
			{
				"type": "ZONE_INFO_DESK",
				"x": 160,
				"y": 12,
				"w": 64,
				"h": 28
			},
			{
				"type": "ZONE_WC",
				"x": 272,
				"y": 12,
				"w": 48,
				"h": 28
			},
			{
				"type": "ZONE_AD",
				"x": 224,
				"y": 12,
				"w": 16,
				"h": 20,
				"meta": {
					"color": [
						1.0,
						0.4,
						0.2
					],
					"name": "ad_color"
				}
			},
			{
				"type": "ZONE_AD",
				"x": 224,
				"y": 36,
				"w": 16,
				"h": 20,
				"meta": {
					"color": [
						0.2,
						0.6,
						1.0
					],
					"name": "ad_color"
				}
			},
			{
				"type": "ZONE_ATM",
				"x": 232,
				"y": 16,
				"w": 16,
				"h": 20
			},
			{
				"type": "ZONE_ATM",
				"x": 232,
				"y": 112,
				"w": 16,
				"h": 20
			},
			{
				"type": "ZONE_CUSTOMER_SERVICE",
				"x": 32,
				"y": 12,
				"w": 64,
				"h": 28,
				"meta": {
					"color": [
						0.5,
						0.55,
						0.7
					],
					"name": "CUSTOMER SERVICE"
				}
			},
			{
				"type": "ZONE_LOYALTY_KIOSK",
				"x": 104,
				"y": 12,
				"w": 56,
				"h": 28,
				"meta": {
					"color": [
						0.6,
						0.5,
						0.75
					],
					"name": "LOYALTY CENTER"
				}
			},
			{
				"type": "ZONE_GIFT_WRAP",
				"x": 168,
				"y": 12,
				"w": 56,
				"h": 28,
				"meta": {
					"color": [
						0.72,
						0.55,
						0.7
					],
					"name": "GIFT WRAPPING"
				}
			},
			{
				"type": "ZONE_DIGITAL_KIOSK",
				"x": 232,
				"y": 44,
				"w": 32,
				"h": 28,
				"meta": {
					"color": [
						0.4,
						0.65,
						0.8
					],
					"name": "INFO KIOSK"
				}
			},
			{
				"type": "ZONE_FOOD_STALL",
				"x": 8,
				"y": 12,
				"w": 56,
				"h": 32,
				"meta": {
					"name": "jp_ramen"
				}
			},
			{
				"type": "ZONE_FOOD_STALL",
				"x": 72,
				"y": 12,
				"w": 56,
				"h": 32,
				"meta": {
					"name": "jp_sushi"
				}
			},
			{
				"type": "ZONE_FOOD_STALL",
				"x": 136,
				"y": 12,
				"w": 56,
				"h": 32,
				"meta": {
					"name": "jp_takoyaki"
				}
			},
			{
				"type": "ZONE_FOOD_STALL",
				"x": 200,
				"y": 12,
				"w": 56,
				"h": 32,
				"meta": {
					"name": "thai"
				}
			},
			{
				"type": "ZONE_FOOD_STALL",
				"x": 264,
				"y": 12,
				"w": 56,
				"h": 32,
				"meta": {
					"name": "indian"
				}
			},
			{
				"type": "ZONE_FOOD_STALL",
				"x": 8,
				"y": 60,
				"w": 56,
				"h": 32,
				"meta": {
					"name": "chinese"
				}
			},
			{
				"type": "ZONE_FOOD_STALL",
				"x": 72,
				"y": 60,
				"w": 56,
				"h": 32,
				"meta": {
					"name": "korean"
				}
			},
			{
				"type": "ZONE_FOOD_STALL",
				"x": 136,
				"y": 60,
				"w": 56,
				"h": 32,
				"meta": {
					"name": "turkish"
				}
			},
			{
				"type": "ZONE_FOOD_STALL",
				"x": 200,
				"y": 60,
				"w": 56,
				"h": 32,
				"meta": {
					"name": "vietnamese"
				}
			},
			{
				"type": "ZONE_FOOD_STALL",
				"x": 264,
				"y": 60,
				"w": 56,
				"h": 32,
				"meta": {
					"name": "italian"
				}
			},
			{
				"type": "ZONE_FOOD_STALL",
				"x": 8,
				"y": 100,
				"w": 56,
				"h": 32,
				"meta": {
					"name": "mexican"
				}
			},
			{
				"type": "ZONE_FOOD_STALL",
				"x": 72,
				"y": 100,
				"w": 56,
				"h": 32,
				"meta": {
					"name": "drinks"
				}
			},
			{
				"type": "ZONE_WAREHOUSE",
				"x": 0,
				"y": 140,
				"w": 480,
				"h": 56,
				"meta": {
					"color": [
						0.55,
						0.45,
						0.38
					],
					"name": "WAREHOUSE FLOOR"
				}
			},
			{
				"type": "ZONE_TRUCK_DOCK",
				"x": 0,
				"y": 140,
				"w": 88,
				"h": 56,
				"meta": {
					"color": [
						0.5,
						0.4,
						0.3
					],
					"name": "TRUCK DOCK"
				}
			},
			{
				"type": "ZONE_FORKLIFT",
				"x": 0,
				"y": 168,
				"w": 88,
				"h": 28,
				"meta": {
					"color": [
						0.8,
						0.6,
						0.2
					],
					"name": "FORKLIFT ZONE"
				}
			},
			{
				"type": "ZONE_CONVEYOR",
				"x": 88,
				"y": 152,
				"w": 200,
				"h": 32,
				"meta": {
					"color": [
						0.6,
						0.6,
						0.65
					],
					"name": "CONVEYOR BELT"
				}
			},
			{
				"type": "ZONE_STORAGE_SHELF",
				"x": 300,
				"y": 140,
				"w": 180,
				"h": 56,
				"meta": {
					"color": [
						0.6,
						0.5,
						0.4
					],
					"name": "STORAGE"
				}
			},
			{
				"type": "ZONE_ELEVATOR",
				"x": 24,
				"y": 8,
				"w": 56,
				"h": 188
			},
			{
				"type": "ZONE_STAIRS",
				"x": 80,
				"y": 8,
				"w": 24,
				"h": 188
			},
			{
				"type": "ZONE_ESCALATOR",
				"x": 104,
				"y": 8,
				"w": 24,
				"h": 188,
				"meta": {
					"escalator_id": "esc_main",
					"direction": 1
				}
			},
			{
				"type": "ZONE_DECOR",
				"x": 64,
				"y": 44,
				"w": 16,
				"h": 16,
				"meta": {
					"name": "dining_table"
				}
			},
			{
				"type": "ZONE_DECOR",
				"x": 136,
				"y": 44,
				"w": 16,
				"h": 16,
				"meta": {
					"name": "dining_table"
				}
			},
			{
				"type": "ZONE_DECOR",
				"x": 208,
				"y": 44,
				"w": 16,
				"h": 16,
				"meta": {
					"name": "dining_table"
				}
			},
			{
				"type": "ZONE_DECOR",
				"x": 280,
				"y": 44,
				"w": 16,
				"h": 16,
				"meta": {
					"name": "dining_table"
				}
			},
			{
				"type": "ZONE_VENDING_MACHINE",
				"x": 280,
				"y": 12,
				"w": 40,
				"h": 40,
				"meta": {
					"name": "Energy Drink $3.00"
				}
			},
			{
				"type": "ZONE_VENDING_MACHINE",
				"x": 280,
				"y": 80,
				"w": 40,
				"h": 40,
				"meta": {
					"name": "Energy Drink $3.00"
				}
			},
			{
				"type": "ZONE_PROMO_BOOTH",
				"x": 12,
				"y": 12,
				"w": 48,
				"h": 32,
				"meta": {
					"color": [
						0.8,
						0.55,
						0.2
					],
					"name": "DAILY DEALS"
				}
			},
			{
				"type": "ZONE_WAREHOUSE_STOCK_VIEW",
				"x": 464,
				"y": 140,
				"w": 40,
				"h": 48,
				"meta": {
					"color": [
						0.45,
						0.6,
						0.45
					],
					"name": "STOCK STATUS"
				}
			},
			{
				"type": "ZONE_LOST_FOUND",
				"x": 88,
				"y": 12,
				"w": 48,
				"h": 28,
				"meta": {
					"color": [
						0.6,
						0.5,
						0.65
					],
					"name": "LOST & FOUND"
				}
			},
			{
				"type": "ZONE_STORE_NEWS",
				"x": 144,
				"y": 12,
				"w": 48,
				"h": 28,
				"meta": {
					"color": [
						0.45,
						0.65,
						0.8
					],
					"name": "STORE NEWS"
				}
			}
		],
		"sections": [],
		"has_shopping": false,
		"has_checkout": false,
		"has_elevator": true,
		"has_stairs": true,
		"is_staff_only": false,
		"is_rooftop": false
	},
	{
		"id": 1,
		"label": "1",
		"theme": "shoes",
		"ambient_color": [
			0.52,
			0.45,
			0.4
		],
		"zones": [
			{
				"type": "ZONE_COMMON",
				"x": 8,
				"y": 12,
				"w": 312,
				"h": 152
			},
			{
				"type": "ZONE_SHOES_RACK",
				"x": 8,
				"y": 12,
				"w": 96,
				"h": 64,
				"meta": {
					"color": [
						0.82,
						0.55,
						0.65
					],
					"name": "LADIES SHOES"
				}
			},
			{
				"type": "ZONE_SHOES_RACK",
				"x": 112,
				"y": 12,
				"w": 96,
				"h": 64,
				"meta": {
					"color": [
						0.55,
						0.6,
						0.8
					],
					"name": "MENS SHOES"
				}
			},
			{
				"type": "ZONE_SHOES_RACK",
				"x": 216,
				"y": 12,
				"w": 96,
				"h": 64,
				"meta": {
					"color": [
						0.7,
						0.75,
						0.9
					],
					"name": "KIDS SHOES"
				}
			},
			{
				"type": "ZONE_SHOES_RACK",
				"x": 8,
				"y": 84,
				"w": 152,
				"h": 64,
				"meta": {
					"color": [
						0.55,
						0.8,
						0.65
					],
					"name": "SPORT SHOES"
				}
			},
			{
				"type": "ZONE_SHOES_RACK",
				"x": 168,
				"y": 84,
				"w": 144,
				"h": 64,
				"meta": {
					"color": [
						0.85,
						0.72,
						0.52
					],
					"name": "SANDALS"
				}
			},
			{
				"type": "ZONE_AD",
				"x": 264,
				"y": 16,
				"w": 16,
				"h": 24,
				"meta": {
					"color": [
						0.2,
						0.8,
						0.5
					],
					"name": "ad_color"
				}
			},
			{
				"type": "ZONE_ELEVATOR",
				"x": 24,
				"y": 8,
				"w": 56,
				"h": 160
			},
			{
				"type": "ZONE_STAIRS",
				"x": 80,
				"y": 8,
				"w": 24,
				"h": 160
			}
		],
		"sections": [
			{
				"id": "shoes_ladies",
				"x": 2,
				"y": 3,
				"w": 24,
				"h": 16
			},
			{
				"id": "shoes_mens",
				"x": 28,
				"y": 3,
				"w": 24,
				"h": 16
			},
			{
				"id": "shoes_kids",
				"x": 54,
				"y": 3,
				"w": 24,
				"h": 16
			}
		],
		"has_shopping": true,
		"has_checkout": true,
		"has_elevator": true,
		"has_stairs": true,
		"is_staff_only": false,
		"is_rooftop": false
	},
	{
		"id": 2,
		"label": "2",
		"theme": "fashion",
		"ambient_color": [
			0.55,
			0.42,
			0.52
		],
		"zones": [
			{
				"type": "ZONE_COMMON",
				"x": 8,
				"y": 12,
				"w": 312,
				"h": 152
			},
			{
				"type": "ZONE_DRESS_RACK",
				"x": 8,
				"y": 12,
				"w": 104,
				"h": 72,
				"meta": {
					"color": [
						0.88,
						0.58,
						0.72
					],
					"name": "LADIES WEAR"
				}
			},
			{
				"type": "ZONE_DRESS_RACK",
				"x": 120,
				"y": 12,
				"w": 104,
				"h": 72,
				"meta": {
					"color": [
						0.6,
						0.68,
						0.88
					],
					"name": "MENS WEAR"
				}
			},
			{
				"type": "ZONE_DRESS_RACK",
				"x": 232,
				"y": 12,
				"w": 80,
				"h": 72,
				"meta": {
					"color": [
						0.72,
						0.8,
						0.95
					],
					"name": "KIDS WEAR"
				}
			},
			{
				"type": "ZONE_DRESS_RACK",
				"x": 8,
				"y": 92,
				"w": 152,
				"h": 56,
				"meta": {
					"color": [
						0.55,
						0.82,
						0.72
					],
					"name": "ACTIVEWEAR"
				}
			},
			{
				"type": "ZONE_DRESS_RACK",
				"x": 168,
				"y": 92,
				"w": 144,
				"h": 56,
				"meta": {
					"color": [
						0.5,
						0.5,
						0.6
					],
					"name": "FORMAL WEAR"
				}
			},
			{
				"type": "ZONE_AD",
				"x": 272,
				"y": 16,
				"w": 16,
				"h": 24,
				"meta": {
					"color": [
						0.95,
						0.4,
						0.8
					],
					"name": "ad_color"
				}
			},
			{
				"type": "ZONE_ELEVATOR",
				"x": 24,
				"y": 8,
				"w": 56,
				"h": 160
			},
			{
				"type": "ZONE_STAIRS",
				"x": 80,
				"y": 8,
				"w": 24,
				"h": 160
			}
		],
		"sections": [
			{
				"id": "ladies_wear",
				"x": 2,
				"y": 3,
				"w": 26,
				"h": 18
			},
			{
				"id": "mens_wear",
				"x": 30,
				"y": 3,
				"w": 26,
				"h": 18
			},
			{
				"id": "kids_wear",
				"x": 58,
				"y": 3,
				"w": 20,
				"h": 18
			}
		],
		"has_shopping": true,
		"has_checkout": true,
		"has_elevator": true,
		"has_stairs": true,
		"is_staff_only": false,
		"is_rooftop": false
	},
	{
		"id": 3,
		"label": "3",
		"theme": "sport",
		"ambient_color": [
			0.4,
			0.5,
			0.55
		],
		"zones": [
			{
				"type": "ZONE_COMMON",
				"x": 8,
				"y": 12,
				"w": 312,
				"h": 152
			},
			{
				"type": "ZONE_SPORT_AREA",
				"x": 8,
				"y": 12,
				"w": 96,
				"h": 64,
				"meta": {
					"color": [
						0.55,
						0.7,
						0.8
					],
					"name": "GYM EQUIPMENT"
				}
			},
			{
				"type": "ZONE_SPORT_AREA",
				"x": 112,
				"y": 12,
				"w": 96,
				"h": 64,
				"meta": {
					"color": [
						0.65,
						0.6,
						0.55
					],
					"name": "SPORTS GEAR"
				}
			},
			{
				"type": "ZONE_SPORT_AREA",
				"x": 216,
				"y": 12,
				"w": 96,
				"h": 64,
				"meta": {
					"color": [
						0.7,
						0.55,
						0.55
					],
					"name": "TEAM SPORTS"
				}
			},
			{
				"type": "ZONE_SPORT_AREA",
				"x": 8,
				"y": 84,
				"w": 152,
				"h": 64,
				"meta": {
					"color": [
						0.55,
						0.78,
						0.68
					],
					"name": "ACTIVEWEAR"
				}
			},
			{
				"type": "ZONE_SPORT_AREA",
				"x": 168,
				"y": 84,
				"w": 144,
				"h": 64,
				"meta": {
					"color": [
						0.6,
						0.75,
						0.82
					],
					"name": "FITNESS"
				}
			},
			{
				"type": "ZONE_AD",
				"x": 280,
				"y": 16,
				"w": 16,
				"h": 24,
				"meta": {
					"color": [
						0.2,
						0.7,
						0.9
					],
					"name": "ad_color"
				}
			},
			{
				"type": "ZONE_ELEVATOR",
				"x": 24,
				"y": 8,
				"w": 56,
				"h": 160
			},
			{
				"type": "ZONE_STAIRS",
				"x": 80,
				"y": 8,
				"w": 24,
				"h": 160
			}
		],
		"sections": [
			{
				"id": "gym",
				"x": 2,
				"y": 3,
				"w": 24,
				"h": 16
			},
			{
				"id": "sports_gear",
				"x": 28,
				"y": 3,
				"w": 24,
				"h": 16
			},
			{
				"id": "activewear",
				"x": 2,
				"y": 21,
				"w": 38,
				"h": 16
			}
		],
		"has_shopping": true,
		"has_checkout": true,
		"has_elevator": true,
		"has_stairs": true,
		"is_staff_only": false,
		"is_rooftop": false
	},
	{
		"id": 4,
		"label": "4",
		"theme": "outdoor",
		"ambient_color": [
			0.42,
			0.55,
			0.45
		],
		"zones": [
			{
				"type": "ZONE_COMMON",
				"x": 8,
				"y": 12,
				"w": 312,
				"h": 152
			},
			{
				"type": "ZONE_OUTDOOR_AREA",
				"x": 8,
				"y": 12,
				"w": 96,
				"h": 64,
				"meta": {
					"color": [
						0.52,
						0.7,
						0.85
					],
					"name": "FISHING"
				}
			},
			{
				"type": "ZONE_OUTDOOR_AREA",
				"x": 112,
				"y": 12,
				"w": 96,
				"h": 64,
				"meta": {
					"color": [
						0.6,
						0.75,
						0.55
					],
					"name": "HIKING"
				}
			},
			{
				"type": "ZONE_OUTDOOR_AREA",
				"x": 216,
				"y": 12,
				"w": 96,
				"h": 64,
				"meta": {
					"color": [
						0.85,
						0.6,
						0.5
					],
					"name": "RUNNING"
				}
			},
			{
				"type": "ZONE_OUTDOOR_AREA",
				"x": 8,
				"y": 84,
				"w": 152,
				"h": 64,
				"meta": {
					"color": [
						0.68,
						0.6,
						0.48
					],
					"name": "CAMPING"
				}
			},
			{
				"type": "ZONE_OUTDOOR_AREA",
				"x": 168,
				"y": 84,
				"w": 144,
				"h": 64,
				"meta": {
					"color": [
						0.55,
						0.65,
						0.72
					],
					"name": "CYCLING"
				}
			},
			{
				"type": "ZONE_AD",
				"x": 280,
				"y": 16,
				"w": 16,
				"h": 24,
				"meta": {
					"color": [
						0.4,
						0.8,
						0.45
					],
					"name": "ad_color"
				}
			},
			{
				"type": "ZONE_ELEVATOR",
				"x": 320,
				"y": 8,
				"w": 16,
				"h": 160
			},
			{
				"type": "ZONE_STAIRS",
				"x": 336,
				"y": 8,
				"w": 24,
				"h": 160
			}
		],
		"sections": [
			{
				"id": "fishing",
				"x": 2,
				"y": 3,
				"w": 24,
				"h": 16
			},
			{
				"id": "hiking",
				"x": 28,
				"y": 3,
				"w": 24,
				"h": 16
			},
			{
				"id": "running",
				"x": 54,
				"y": 3,
				"w": 24,
				"h": 16
			}
		],
		"has_shopping": true,
		"has_checkout": true,
		"has_elevator": true,
		"has_stairs": true,
		"is_staff_only": false,
		"is_rooftop": false
	},
	{
		"id": 5,
		"label": "5",
		"theme": "stationery",
		"ambient_color": [
			0.48,
			0.55,
			0.45
		],
		"zones": [
			{
				"type": "ZONE_COMMON",
				"x": 8,
				"y": 12,
				"w": 312,
				"h": 152
			},
			{
				"type": "ZONE_STATIONERY",
				"x": 8,
				"y": 12,
				"w": 144,
				"h": 72,
				"meta": {
					"color": [
						0.75,
						0.78,
						0.9
					],
					"name": "STATIONERY"
				}
			},
			{
				"type": "ZONE_STATIONERY",
				"x": 160,
				"y": 12,
				"w": 152,
				"h": 72,
				"meta": {
					"color": [
						0.7,
						0.75,
						0.82
					],
					"name": "OFFICE SUPPLIES"
				}
			},
			{
				"type": "ZONE_PLANTS_AREA",
				"x": 8,
				"y": 92,
				"w": 152,
				"h": 56,
				"meta": {
					"color": [
						0.55,
						0.82,
						0.6
					],
					"name": "INDOOR PLANTS"
				}
			},
			{
				"type": "ZONE_PLANTS_AREA",
				"x": 168,
				"y": 92,
				"w": 144,
				"h": 56,
				"meta": {
					"color": [
						0.68,
						0.82,
						0.52
					],
					"name": "GARDEN PLANTS"
				}
			},
			{
				"type": "ZONE_AD",
				"x": 288,
				"y": 16,
				"w": 16,
				"h": 24,
				"meta": {
					"color": [
						0.6,
						0.75,
						1.0
					],
					"name": "ad_color"
				}
			},
			{
				"type": "ZONE_ELEVATOR",
				"x": 320,
				"y": 8,
				"w": 16,
				"h": 160
			},
			{
				"type": "ZONE_STAIRS",
				"x": 336,
				"y": 8,
				"w": 24,
				"h": 160
			}
		],
		"sections": [
			{
				"id": "stationery",
				"x": 2,
				"y": 3,
				"w": 36,
				"h": 18
			},
			{
				"id": "plants",
				"x": 2,
				"y": 23,
				"w": 38,
				"h": 14
			}
		],
		"has_shopping": true,
		"has_checkout": true,
		"has_elevator": true,
		"has_stairs": true,
		"is_staff_only": false,
		"is_rooftop": false
	},
	{
		"id": 6,
		"label": "6",
		"theme": "staff_area",
		"ambient_color": [
			0.38,
			0.38,
			0.4
		],
		"zones": [
			{
				"type": "ZONE_COMMON",
				"x": 8,
				"y": 12,
				"w": 312,
				"h": 152
			},
			{
				"type": "ZONE_LOCKER",
				"x": 8,
				"y": 12,
				"w": 120,
				"h": 80,
				"meta": {
					"color": [
						0.45,
						0.45,
						0.5
					],
					"name": "LOCKER ROOM"
				}
			},
			{
				"type": "ZONE_STAFF_LOUNGE",
				"x": 136,
				"y": 12,
				"w": 120,
				"h": 80,
				"meta": {
					"color": [
						0.52,
						0.48,
						0.44
					],
					"name": "STAFF LOUNGE"
				}
			},
			{
				"type": "ZONE_TRAINING",
				"x": 8,
				"y": 100,
				"w": 200,
				"h": 56,
				"meta": {
					"color": [
						0.4,
						0.48,
						0.55
					],
					"name": "TRAINING ROOM"
				}
			},
			{
				"type": "ZONE_ELEVATOR",
				"x": 320,
				"y": 8,
				"w": 16,
				"h": 160
			},
			{
				"type": "ZONE_STAIRS",
				"x": 336,
				"y": 8,
				"w": 24,
				"h": 160
			}
		],
		"sections": [],
		"has_shopping": false,
		"has_checkout": false,
		"has_elevator": true,
		"has_stairs": true,
		"is_staff_only": true,
		"is_rooftop": false
	},
	{
		"id": 7,
		"label": "7",
		"theme": "back_office",
		"ambient_color": [
			0.4,
			0.42,
			0.45
		],
		"zones": [
			{
				"type": "ZONE_COMMON",
				"x": 8,
				"y": 12,
				"w": 312,
				"h": 152
			},
			{
				"type": "ZONE_OFFICE_DESK",
				"x": 8,
				"y": 12,
				"w": 152,
				"h": 72,
				"meta": {
					"color": [
						0.48,
						0.52,
						0.58
					],
					"name": "ADMIN OFFICE"
				}
			},
			{
				"type": "ZONE_OFFICE_DESK",
				"x": 168,
				"y": 12,
				"w": 144,
				"h": 72,
				"meta": {
					"color": [
						0.55,
						0.5,
						0.58
					],
					"name": "HR DEPARTMENT"
				}
			},
			{
				"type": "ZONE_OFFICE_DESK",
				"x": 8,
				"y": 92,
				"w": 312,
				"h": 56,
				"meta": {
					"color": [
						0.45,
						0.5,
						0.55
					],
					"name": "OPEN OFFICE"
				}
			},
			{
				"type": "ZONE_MONITOR_ROOM",
				"x": 264,
				"y": 12,
				"w": 48,
				"h": 140,
				"meta": {
					"color": [
						0.2,
						0.25,
						0.3
					],
					"name": "MONITORING ROOM"
				}
			},
			{
				"type": "ZONE_ELEVATOR",
				"x": 320,
				"y": 8,
				"w": 16,
				"h": 160
			},
			{
				"type": "ZONE_STAIRS",
				"x": 336,
				"y": 8,
				"w": 24,
				"h": 160
			}
		],
		"sections": [],
		"has_shopping": false,
		"has_checkout": false,
		"has_elevator": true,
		"has_stairs": true,
		"is_staff_only": true,
		"is_rooftop": false
	},
	{
		"id": 8,
		"label": "8",
		"theme": "arcade",
		"ambient_color": [
			0.22,
			0.18,
			0.38
		],
		"zones": [
			{
				"type": "ZONE_COMMON",
				"x": 8,
				"y": 12,
				"w": 312,
				"h": 152
			},
			{
				"type": "ZONE_KIDS_PLAY",
				"x": 40,
				"y": 12,
				"w": 120,
				"h": 80,
				"meta": {
					"color": [
						0.4,
						0.55,
						0.8
					],
					"name": "PLAY ZONE"
				}
			},
			{
				"type": "ZONE_CLAW_MACHINE",
				"x": 8,
				"y": 12,
				"w": 40,
				"h": 56,
				"meta": {
					"name": "prize_pool"
				}
			},
			{
				"type": "ZONE_CLAW_MACHINE",
				"x": 56,
				"y": 12,
				"w": 40,
				"h": 56,
				"meta": {
					"name": "prize_pool"
				}
			},
			{
				"type": "ZONE_CLAW_MACHINE",
				"x": 8,
				"y": 80,
				"w": 40,
				"h": 56,
				"meta": {
					"name": "prize_pool"
				}
			},
			{
				"type": "ZONE_CLAW_MACHINE",
				"x": 56,
				"y": 80,
				"w": 40,
				"h": 56,
				"meta": {
					"name": "prize_pool"
				}
			},
			{
				"type": "ZONE_ELEVATOR",
				"x": 320,
				"y": 8,
				"w": 16,
				"h": 160
			},
			{
				"type": "ZONE_STAIRS",
				"x": 336,
				"y": 8,
				"w": 24,
				"h": 160
			}
		],
		"sections": [],
		"has_shopping": false,
		"has_checkout": false,
		"has_elevator": true,
		"has_stairs": true,
		"is_staff_only": true,
		"is_rooftop": false
	},
	{
		"id": 9,
		"label": "9",
		"theme": "staff_room",
		"ambient_color": [
			0.38,
			0.42,
			0.5
		],
		"zones": [
			{
				"type": "ZONE_COMMON",
				"x": 8,
				"y": 12,
				"w": 312,
				"h": 152
			},
			{
				"type": "ZONE_OFFICE_DESK",
				"x": 40,
				"y": 12,
				"w": 120,
				"h": 80,
				"meta": {
					"color": [
						0.4,
						0.55,
						0.65
					],
					"name": "terminal"
				}
			},
			{
				"type": "ZONE_STAFF_LOUNGE",
				"x": 168,
				"y": 12,
				"w": 136,
				"h": 80,
				"meta": {
					"color": [
						0.45,
						0.45,
						0.5
					],
					"name": "STAFF AREA"
				}
			},
			{
				"type": "ZONE_TRAINING",
				"x": 8,
				"y": 100,
				"w": 312,
				"h": 56,
				"meta": {
					"color": [
						0.38,
						0.48,
						0.55
					],
					"name": "OPERATIONS CENTER"
				}
			},
			{
				"type": "ZONE_ELEVATOR",
				"x": 320,
				"y": 8,
				"w": 16,
				"h": 160
			}
		],
		"sections": [],
		"has_shopping": false,
		"has_checkout": false,
		"has_elevator": true,
		"has_stairs": true,
		"is_staff_only": true,
		"is_rooftop": true
	},
	{
		"id": 10,
		"label": "10",
		"theme": "rooftop",
		"ambient_color": [
			0.6,
			0.55,
			0.45
		],
		"zones": [
			{
				"type": "ZONE_COMMON",
				"x": 8,
				"y": 12,
				"w": 312,
				"h": 152
			},
			{
				"type": "ZONE_CAFE_COUNTER",
				"x": 40,
				"y": 12,
				"w": 80,
				"h": 56,
				"meta": {
					"name": "Smoothie $5.50"
				}
			},
			{
				"type": "ZONE_AD",
				"x": 288,
				"y": 16,
				"w": 16,
				"h": 24,
				"meta": {
					"color": [
						0.8,
						0.6,
						0.3
					],
					"name": "ad_color"
				}
			},
			{
				"type": "ZONE_ELEVATOR",
				"x": 320,
				"y": 8,
				"w": 16,
				"h": 160
			},
			{
				"type": "ZONE_STAIRS",
				"x": 336,
				"y": 8,
				"w": 24,
				"h": 160
			}
		],
		"sections": [],
		"has_shopping": true,
		"has_checkout": false,
		"has_elevator": true,
		"has_stairs": true,
		"is_staff_only": false,
		"is_rooftop": false
	},
	{
		"id": 11,
		"label": "11",
		"theme": "warehouse",
		"ambient_color": [
			0.55,
			0.45,
			0.38
		],
		"zones": [
			{
				"type": "ZONE_WAREHOUSE",
				"x": 8,
				"y": 12,
				"w": 312,
				"h": 152
			},
			{
				"type": "ZONE_TRUCK_DOCK",
				"x": 8,
				"y": 12,
				"w": 80,
				"h": 56,
				"meta": {
					"color": [
						0.5,
						0.4,
						0.3
					],
					"name": "TRUCK DOCK"
				}
			},
			{
				"type": "ZONE_FORKLIFT",
				"x": 8,
				"y": 76,
				"w": 80,
				"h": 48,
				"meta": {
					"color": [
						0.8,
						0.6,
						0.2
					],
					"name": "FORKLIFT"
				}
			},
			{
				"type": "ZONE_CONVEYOR",
				"x": 96,
				"y": 12,
				"w": 120,
				"h": 48,
				"meta": {
					"color": [
						0.6,
						0.6,
						0.65
					],
					"name": "CONVEYOR BELT"
				}
			},
			{
				"type": "ZONE_PACKING_STATION",
				"x": 96,
				"y": 76,
				"w": 120,
				"h": 48,
				"meta": {
					"color": [
						0.4,
						0.7,
						0.5
					],
					"name": "PACKING STATION"
				}
			},
			{
				"type": "ZONE_AD",
				"x": 240,
				"y": 16,
				"w": 16,
				"h": 24,
				"meta": {
					"color": [
						0.9,
						0.7,
						0.2
					],
					"name": "ad_color"
				}
			},
			{
				"type": "ZONE_ELEVATOR",
				"x": 320,
				"y": 8,
				"w": 16,
				"h": 160
			}
		],
		"sections": [],
		"has_shopping": false,
		"has_checkout": false,
		"has_elevator": true,
		"has_stairs": false,
		"is_staff_only": false,
		"is_rooftop": false
	},
	{
		"id": 12,
		"label": "12",
		"theme": "juice_bar",
		"ambient_color": [
			0.55,
			0.72,
			0.58
		],
		"zones": [
			{
				"type": "ZONE_COMMON",
				"x": 8,
				"y": 12,
				"w": 312,
				"h": 152
			},
			{
				"type": "ZONE_JUICE_BAR",
				"x": 8,
				"y": 12,
				"w": 120,
				"h": 80,
				"meta": {
					"color": [
						1.0,
						0.75,
						0.3
					],
					"name": "JUICE BAR"
				}
			},
			{
				"type": "ZONE_HEALTH_FOOD",
				"x": 136,
				"y": 12,
				"w": 120,
				"h": 80,
				"meta": {
					"color": [
						0.55,
						0.82,
						0.58
					],
					"name": "HEALTH FOODS"
				}
			},
			{
				"type": "ZONE_SMOOTHIE",
				"x": 8,
				"y": 100,
				"w": 120,
				"h": 56,
				"meta": {
					"color": [
						0.8,
						0.55,
						0.8
					],
					"name": "SMOOTHIE STATION"
				}
			},
			{
				"type": "ZONE_SALAD_BAR",
				"x": 136,
				"y": 100,
				"w": 120,
				"h": 56,
				"meta": {
					"color": [
						0.6,
						0.85,
						0.6
					],
					"name": "SALAD BAR"
				}
			},
			{
				"type": "ZONE_AD",
				"x": 264,
				"y": 16,
				"w": 16,
				"h": 24,
				"meta": {
					"color": [
						0.4,
						0.9,
						0.5
					],
					"name": "ad_color"
				}
			},
			{
				"type": "ZONE_ELEVATOR",
				"x": 320,
				"y": 8,
				"w": 16,
				"h": 160
			},
			{
				"type": "ZONE_STAIRS",
				"x": 336,
				"y": 8,
				"w": 24,
				"h": 160
			}
		],
		"sections": [
			{
				"id": "juice",
				"x": 2,
				"y": 3,
				"w": 30,
				"h": 20
			},
			{
				"id": "health",
				"x": 34,
				"y": 3,
				"w": 30,
				"h": 20
			}
		],
		"has_shopping": true,
		"has_checkout": false,
		"has_elevator": true,
		"has_stairs": true,
		"is_staff_only": false,
		"is_rooftop": false
	},
	{
		"id": 13,
		"label": "13",
		"theme": "kids_kingdom",
		"ambient_color": [
			0.72,
			0.58,
			0.8
		],
		"zones": [
			{
				"type": "ZONE_COMMON",
				"x": 8,
				"y": 12,
				"w": 312,
				"h": 152
			},
			{
				"type": "ZONE_KIDS_PLAY",
				"x": 8,
				"y": 12,
				"w": 112,
				"h": 80,
				"meta": {
					"color": [
						0.6,
						0.8,
						0.9
					],
					"name": "PLAY ZONE"
				}
			},
			{
				"type": "ZONE_KIDS_CLUB",
				"x": 128,
				"y": 12,
				"w": 96,
				"h": 80,
				"meta": {
					"color": [
						0.9,
						0.6,
						0.8
					],
					"name": "KIDS CLUB"
				}
			},
			{
				"type": "ZONE_NURSING_ROOM",
				"x": 232,
				"y": 12,
				"w": 80,
				"h": 48,
				"meta": {
					"color": [
						0.85,
						0.75,
						0.9
					],
					"name": "NURSERY"
				}
			},
			{
				"type": "ZONE_WC",
				"x": 232,
				"y": 68,
				"w": 80,
				"h": 48,
				"meta": {
					"color": [
						0.7,
						0.65,
						0.8
					],
					"name": "FAMILY WC"
				}
			},
			{
				"type": "ZONE_STAIRS",
				"x": 312,
				"y": 8,
				"w": 16,
				"h": 160
			},
			{
				"type": "ZONE_ELEVATOR",
				"x": 332,
				"y": 8,
				"w": 16,
				"h": 160
			}
		],
		"sections": [
			{
				"id": "toys",
				"x": 2,
				"y": 3,
				"w": 28,
				"h": 20
			}
		],
		"has_shopping": true,
		"has_checkout": true,
		"has_elevator": true,
		"has_stairs": true,
		"is_staff_only": false,
		"is_rooftop": false
	},
	{
		"id": 14,
		"label": "14",
		"theme": "electronics",
		"ambient_color": [
			0.35,
			0.45,
			0.65
		],
		"zones": [
			{
				"type": "ZONE_COMMON",
				"x": 8,
				"y": 12,
				"w": 312,
				"h": 152
			},
			{
				"type": "ZONE_PHONE_GADGETS",
				"x": 8,
				"y": 12,
				"w": 120,
				"h": 72,
				"meta": {
					"color": [
						0.35,
						0.55,
						0.8
					],
					"name": "PHONES & GADGETS"
				}
			},
			{
				"type": "ZONE_SMART_HOME",
				"x": 136,
				"y": 12,
				"w": 120,
				"h": 72,
				"meta": {
					"color": [
						0.4,
						0.6,
						0.7
					],
					"name": "SMART HOME"
				}
			},
			{
				"type": "ZONE_ELECTRONICS",
				"x": 8,
				"y": 92,
				"w": 152,
				"h": 64,
				"meta": {
					"color": [
						0.45,
						0.5,
						0.65
					],
					"name": "ELECTRONICS"
				}
			},
			{
				"type": "ZONE_REPAIR_COUNTER",
				"x": 168,
				"y": 92,
				"w": 144,
				"h": 64,
				"meta": {
					"color": [
						0.6,
						0.45,
						0.4
					],
					"name": "REPAIR COUNTER"
				}
			},
			{
				"type": "ZONE_AD",
				"x": 264,
				"y": 16,
				"w": 16,
				"h": 24,
				"meta": {
					"color": [
						0.3,
						0.6,
						1.0
					],
					"name": "ad_color"
				}
			},
			{
				"type": "ZONE_ELEVATOR",
				"x": 320,
				"y": 8,
				"w": 16,
				"h": 160
			},
			{
				"type": "ZONE_STAIRS",
				"x": 336,
				"y": 8,
				"w": 24,
				"h": 160
			}
		],
		"sections": [],
		"has_shopping": true,
		"has_checkout": true,
		"has_elevator": true,
		"has_stairs": false,
		"is_staff_only": true,
		"is_rooftop": true
	},
	{
		"id": 15,
		"label": "15",
		"theme": "canteen",
		"ambient_color": [
			0.55,
			0.5,
			0.42
		],
		"zones": [
			{
				"type": "ZONE_COMMON",
				"x": 8,
				"y": 12,
				"w": 312,
				"h": 152
			},
			{
				"type": "ZONE_CANTEEN",
				"x": 8,
				"y": 12,
				"w": 304,
				"h": 32,
				"meta": {
					"color": [
						0.7,
						0.65,
						0.55
					],
					"name": "CANTEEN COUNTER"
				}
			},
			{
				"type": "ZONE_FOOD_STALL",
				"x": 8,
				"y": 12,
				"w": 48,
				"h": 32,
				"meta": {
					"name": "canteen_rice"
				}
			},
			{
				"type": "ZONE_FOOD_STALL",
				"x": 64,
				"y": 12,
				"w": 48,
				"h": 32,
				"meta": {
					"name": "canteen_noodle"
				}
			},
			{
				"type": "ZONE_FOOD_STALL",
				"x": 120,
				"y": 12,
				"w": 48,
				"h": 32,
				"meta": {
					"name": "canteen_meat"
				}
			},
			{
				"type": "ZONE_FOOD_STALL",
				"x": 176,
				"y": 12,
				"w": 48,
				"h": 32,
				"meta": {
					"name": "canteen_veg"
				}
			},
			{
				"type": "ZONE_FOOD_STALL",
				"x": 232,
				"y": 12,
				"w": 48,
				"h": 32,
				"meta": {
					"name": "canteen_drinks"
				}
			},
			{
				"type": "ZONE_FOOD_STALL",
				"x": 280,
				"y": 12,
				"w": 32,
				"h": 32,
				"meta": {
					"name": "canteen_fruit"
				}
			},
			{
				"type": "ZONE_DECOR",
				"x": 16,
				"y": 56,
				"w": 288,
				"h": 88,
				"meta": {
					"name": "canteen_tables"
				}
			},
			{
				"type": "ZONE_ENTRY_GATE",
				"x": 152,
				"y": 12,
				"w": 24,
				"h": 20,
				"meta": {
					"color": [
						0.8,
						0.7,
						0.3
					],
					"name": "CANTEEN ENTRANCE"
				}
			},
			{
				"type": "ZONE_ELEVATOR",
				"x": 320,
				"y": 8,
				"w": 16,
				"h": 160
			},
			{
				"type": "ZONE_STAIRS",
				"x": 336,
				"y": 8,
				"w": 24,
				"h": 160
			}
		],
		"sections": [],
		"has_shopping": true,
		"has_checkout": false,
		"has_elevator": true,
		"has_stairs": false,
		"is_staff_only": false,
		"is_rooftop": false
	},
	{
		"id": 16,
		"label": "16",
		"theme": "food_court",
		"ambient_color": [
			0.58,
			0.45,
			0.35
		],
		"zones": [
			{
				"type": "ZONE_COMMON",
				"x": 8,
				"y": 12,
				"w": 312,
				"h": 152
			},
			{
				"type": "ZONE_FOOD_STALL",
				"x": 8,
				"y": 12,
				"w": 56,
				"h": 32,
				"meta": {
					"name": "burger_king_style"
				}
			},
			{
				"type": "ZONE_FOOD_STALL",
				"x": 72,
				"y": 12,
				"w": 56,
				"h": 32,
				"meta": {
					"name": "pizza_hut_style"
				}
			},
			{
				"type": "ZONE_FOOD_STALL",
				"x": 136,
				"y": 12,
				"w": 56,
				"h": 32,
				"meta": {
					"name": "fried_chicken_style"
				}
			},
			{
				"type": "ZONE_FOOD_STALL",
				"x": 200,
				"y": 12,
				"w": 56,
				"h": 32,
				"meta": {
					"name": "hot_dog_style"
				}
			},
			{
				"type": "ZONE_FOOD_STALL",
				"x": 264,
				"y": 12,
				"w": 56,
				"h": 32,
				"meta": {
					"name": "ice_cream_style"
				}
			},
			{
				"type": "ZONE_FOOD_COURT",
				"x": 8,
				"y": 56,
				"w": 304,
				"h": 88,
				"meta": {
					"color": [
						0.6,
						0.5,
						0.4
					],
					"name": "FOOD COURT SEATING"
				}
			},
			{
				"type": "ZONE_DECOR",
				"x": 24,
				"y": 56,
				"w": 16,
				"h": 16,
				"meta": {
					"name": "trash_bin"
				}
			},
			{
				"type": "ZONE_DECOR",
				"x": 120,
				"y": 56,
				"w": 16,
				"h": 16,
				"meta": {
					"name": "trash_bin"
				}
			},
			{
				"type": "ZONE_DECOR",
				"x": 216,
				"y": 56,
				"w": 16,
				"h": 16,
				"meta": {
					"name": "trash_bin"
				}
			},
			{
				"type": "ZONE_DECOR",
				"x": 288,
				"y": 56,
				"w": 16,
				"h": 16,
				"meta": {
					"name": "trash_bin"
				}
			},
			{
				"type": "ZONE_ELEVATOR",
				"x": 320,
				"y": 8,
				"w": 16,
				"h": 160
			},
			{
				"type": "ZONE_STAIRS",
				"x": 336,
				"y": 8,
				"w": 24,
				"h": 160
			}
		],
		"sections": [],
		"has_shopping": true,
		"has_checkout": false,
		"has_elevator": true,
		"has_stairs": false,
		"is_staff_only": false,
		"is_rooftop": false
	},
	{
		"id": 17,
		"label": "17",
		"theme": "entertainment",
		"ambient_color": [
			0.35,
			0.25,
			0.5
		],
		"zones": [
			{
				"type": "ZONE_COMMON",
				"x": 8,
				"y": 12,
				"w": 312,
				"h": 152
			},
			{
				"type": "ZONE_KARAOKE",
				"x": 8,
				"y": 12,
				"w": 112,
				"h": 80,
				"meta": {
					"color": [
						0.25,
						0.18,
						0.38
					],
					"name": "KARAOKE ROOMS"
				}
			},
			{
				"type": "ZONE_POOL_TABLE",
				"x": 128,
				"y": 12,
				"w": 80,
				"h": 40,
				"meta": {
					"color": [
						0.28,
						0.52,
						0.38
					],
					"name": "POOL AREA"
				}
			},
			{
				"type": "ZONE_DARTS_BOARD",
				"x": 128,
				"y": 64,
				"w": 40,
				"h": 40,
				"meta": {
					"color": [
						0.3,
						0.32,
						0.25
					],
					"name": "DARTS"
				}
			},
			{
				"type": "ZONE_CLAW_MACHINE",
				"x": 216,
				"y": 12,
				"w": 32,
				"h": 32,
				"meta": {
					"color": [
						0.5,
						0.3,
						0.7
					],
					"name": "CLAW MACHINE 1"
				}
			},
			{
				"type": "ZONE_CLAW_MACHINE",
				"x": 216,
				"y": 52,
				"w": 32,
				"h": 32,
				"meta": {
					"color": [
						0.4,
						0.5,
						0.7
					],
					"name": "CLAW MACHINE 2"
				}
			},
			{
				"type": "ZONE_CLAW_MACHINE",
				"x": 216,
				"y": 92,
				"w": 32,
				"h": 32,
				"meta": {
					"color": [
						0.7,
						0.4,
						0.5
					],
					"name": "CLAW MACHINE 3"
				}
			},
			{
				"type": "ZONE_DECOR",
				"x": 256,
				"y": 12,
				"w": 56,
				"h": 56,
				"meta": {
					"name": "arcade_machines"
				}
			},
			{
				"type": "ZONE_DECOR",
				"x": 256,
				"y": 76,
				"w": 56,
				"h": 72,
				"meta": {
					"name": "lounge_seating"
				}
			},
			{
				"type": "ZONE_AD",
				"x": 256,
				"y": 12,
				"w": 16,
				"h": 20,
				"meta": {
					"color": [
						0.8,
						0.2,
						0.8
					],
					"name": "ad_color"
				}
			},
			{
				"type": "ZONE_ELEVATOR",
				"x": 320,
				"y": 8,
				"w": 16,
				"h": 160
			},
			{
				"type": "ZONE_STAIRS",
				"x": 336,
				"y": 8,
				"w": 24,
				"h": 160
			}
		],
		"sections": [],
		"has_shopping": true,
		"has_checkout": false,
		"has_elevator": true,
		"has_stairs": false,
		"is_staff_only": false,
		"is_rooftop": false
	}
]